onwut/__init__.py
onwut/main.py
onwut/migrate.py
onwut/onwut_data.db
onwut/scraper.py
onwut-1.8.dist-info/LICENSE
onwut-1.8.dist-info/METADATA
onwut-1.8.dist-info/WHEEL
onwut-1.8.dist-info/top_level.txt
onwut-1.8.dist-info/RECORD
