Metadata-Version: 2.1
Name: onwut
Version: 1.8
Summary: onwut は、経済産業省のウェブサイトからPDFレポートをスクレイピングして処理するためのPythonライブラリです。
Home-page: https://github.com/yourusername/onwut
Author: Your Name
Author-email: your.email@example.com
License-File: LICENSE
Requires-Dist: requests
Requires-Dist: beautifulsoup4
Requires-Dist: PyPDF2
Requires-Dist: lxml
